pyHASSClever/__init__.py
pyHASSClever/availability.py
pyHASSClever/const.py
pyHASSClever/exceptions.py
pyHASSClever/locations.py
pyHASSClever-0.0.0.dist-info/LICENSE
pyHASSClever-0.0.0.dist-info/METADATA
pyHASSClever-0.0.0.dist-info/WHEEL
pyHASSClever-0.0.0.dist-info/top_level.txt
pyHASSClever-0.0.0.dist-info/RECORD
