Metadata-Version: 2.1
Name: pyHASSClever
Version: 0.0.0
Summary: Unofficial Clever Chargepoints API library
Home-page: https://github.com/mtrab/pyHASSClever
Author: Malene Trab
Author-email: malene@trab.dk
License: MIT
Project-URL: Bug Tracker, https://github.com/mtrab/pyHASSClever/issues
License-File: LICENSE
Requires-Dist: requests (>=2.26.0)
